Metadata-Version: 2.4
Name: mseep-synalinks
Version: 1.0.0
Summary: Graph-Based Programmable Neuro-Symbolic LM Framework
Home-page: https://github.com/mseep
Author: mseep
Author-email: support@skydeck.ai
Maintainer: mseep
Maintainer-email: support@skydeck.ai
Keywords: mseep
Classifier: Programming Language :: Python :: 3
Classifier: License :: OSI Approved :: MIT License
Classifier: Operating System :: OS Independent
Requires-Python: >=3.6
License-File: LICENSE
Requires-Dist: absl-py
Requires-Dist: asyncio
Requires-Dist: click
Requires-Dist: datasets
Requires-Dist: docstring-parser
Requires-Dist: graphviz
Requires-Dist: inquirer
Requires-Dist: jinja2
Requires-Dist: litellm
Requires-Dist: matplotlib
Requires-Dist: namex
Requires-Dist: neo4j
Requires-Dist: nest-asyncio
Requires-Dist: numpy
Requires-Dist: optree
Requires-Dist: pydantic
Requires-Dist: pydotplus
Requires-Dist: rich
Requires-Dist: sentry-sdk
Dynamic: author
Dynamic: author-email
Dynamic: classifier
Dynamic: description
Dynamic: description-content-type
Dynamic: home-page
Dynamic: keywords
Dynamic: license-file
Dynamic: maintainer
Dynamic: maintainer-email
Dynamic: requires-dist
Dynamic: requires-python
Dynamic: summary
